{
    "delphi-epicast": {
        "target_end_date": [
            "2016-05-14",
            "2016-05-21",
            "2016-05-28",
            "2016-06-04"
        ],
        "q0.025": [
            0.50488422175927,
            0.5,
            0.5,
            0.5
        ],
        "q0.25": [
            0.632403970912847,
            0.591948887652167,
            0.591948887652167,
            0.591948887652167
        ],
        "q0.5": [
            0.774092581083489,
            0.739828624657164,
            0.739828624657164,
            0.739828624657164
        ],
        "q0.75": [
            0.915781191254131,
            0.887708361662162,
            0.887708361662162,
            0.887708361662162
        ],
        "q0.975": [
            1.4949213959395,
            1.48969881031495,
            1.48969881031495,
            1.48969881031495
        ]
    },
    "hist-avg": {
        "target_end_date": [
            "2016-05-14",
            "2016-05-21",
            "2016-05-28",
            "2016-06-04"
        ],
        "q0.025": [
            0.5,
            0.5,
            0.5,
            0.5
        ],
        "q0.25": [
            0.5,
            0.5,
            0.5,
            0.5
        ],
        "q0.5": [
            0.5,
            0.5,
            0.5,
            0.5
        ],
        "q0.75": [
            0.841325950974374,
            0.747661522784846,
            0.796502851946488,
            0.833885072045184
        ],
        "q0.975": [
            3.64100342357818,
            1.46036550093227,
            9.00514543869137,
            8.14486525589332
        ]
    }
}