{
    "UGA_CEID-Walk": {
        "target_end_date": [
            "2025-05-03",
            "2025-05-10",
            "2025-05-17",
            "2025-05-24"
        ],
        "q0.025": [
            0.0,
            0.0,
            0.0,
            0.0
        ],
        "q0.25": [
            8.329,
            0.0,
            0.0,
            0.0
        ],
        "q0.5": [
            86.879,
            106.622,
            101.637,
            100.132
        ],
        "q0.75": [
            149.124,
            196.478,
            212.949,
            223.564
        ],
        "q0.975": [
            289.67,
            365.496,
            485.358,
            489.22
        ]
    },
    "CU-ensemble": {
        "target_end_date": [
            "2025-05-03",
            "2025-05-10",
            "2025-05-17",
            "2025-05-24"
        ],
        "q0.025": [
            9.0,
            6.0,
            2.0,
            2.0
        ],
        "q0.25": [
            28.0,
            20.0,
            12.0,
            10.0
        ],
        "q0.5": [
            45.0,
            37.0,
            32.0,
            32.0
        ],
        "q0.75": [
            74.0,
            67.0,
            68.0,
            64.0
        ],
        "q0.975": [
            169.0,
            190.0,
            220.0,
            241.0
        ]
    },
    "fjordhest-ensemble": {
        "target_end_date": [
            "2025-05-03",
            "2025-05-10",
            "2025-05-17",
            "2025-05-24"
        ],
        "q0.025": [
            9.93,
            4.49,
            1.5,
            0.0
        ],
        "q0.25": [
            15.18,
            8.34,
            4.49,
            2.53
        ],
        "q0.5": [
            46.04,
            33.05,
            11.72,
            4.21
        ],
        "q0.75": [
            97.55,
            97.1,
            68.81,
            48.43
        ],
        "q0.975": [
            205.93,
            228.0,
            197.7,
            144.15
        ]
    },
    "UGuelph-CompositeCurve": {
        "target_end_date": [
            "2025-04-26",
            "2025-05-03",
            "2025-05-10",
            "2025-05-17",
            "2025-05-24"
        ],
        "q0.025": [
            81.0,
            59.0,
            48.0,
            44.0,
            34.0
        ],
        "q0.25": [
            81.0,
            65.0,
            56.0,
            49.0,
            45.0
        ],
        "q0.5": [
            81.0,
            69.0,
            61.0,
            52.0,
            48.0
        ],
        "q0.75": [
            81.0,
            72.0,
            66.0,
            56.0,
            52.0
        ],
        "q0.975": [
            81.0,
            81.0,
            71.0,
            64.0,
            55.0
        ]
    },
    "VTSanghani-PRIME": {
        "target_end_date": [
            "2025-04-26",
            "2025-05-03",
            "2025-05-10",
            "2025-05-17",
            "2025-05-24"
        ],
        "q0.025": [
            21.0,
            0.0,
            0.0,
            0.0,
            0.0
        ],
        "q0.25": [
            40.0,
            11.0,
            3.0,
            1.0,
            0.0
        ],
        "q0.5": [
            66.0,
            37.0,
            29.0,
            27.0,
            22.0
        ],
        "q0.75": [
            93.0,
            64.0,
            56.0,
            54.0,
            49.0
        ],
        "q0.975": [
            112.0,
            83.0,
            75.0,
            73.0,
            68.0
        ]
    },
    "UVAFluX-CESGCN": {
        "target_end_date": [
            "2025-04-26",
            "2025-05-03",
            "2025-05-10",
            "2025-05-17",
            "2025-05-24"
        ],
        "q0.025": [
            51.1869010925293,
            63.67137384414673,
            69.69796562194824,
            94.60032901763915,
            108.14038944244385
        ],
        "q0.25": [
            51.1869010925293,
            76.08335685729979,
            71.77834129333495,
            99.99254989624023,
            109.08007431030272
        ],
        "q0.5": [
            72.95777130126953,
            91.78738403320312,
            73.0097541809082,
            106.81505966186523,
            110.26900100708008
        ],
        "q0.75": [
            195.3881072998047,
            142.44126892089844,
            137.22354125976562,
            128.8211669921875,
            114.10391235351562
        ],
        "q0.975": [
            195.3881072998047,
            142.44126892089844,
            137.22354125976562,
            128.8211669921875,
            114.10391235351562
        ]
    },
    "Gatech-ensemble_prob": {
        "target_end_date": [
            "2025-05-03",
            "2025-05-10",
            "2025-05-17",
            "2025-05-24"
        ],
        "q0.025": [
            28.0,
            5.0,
            3.0,
            0.0
        ],
        "q0.25": [
            67.0,
            41.0,
            53.0,
            0.0
        ],
        "q0.5": [
            94.0,
            73.0,
            103.0,
            2.0
        ],
        "q0.75": [
            126.0,
            115.0,
            169.0,
            21.0
        ],
        "q0.975": [
            198.0,
            220.0,
            341.0,
            112.0
        ]
    },
    "NEU_ISI-AdaptiveEnsemble": {
        "target_end_date": [
            "2025-05-03",
            "2025-05-10",
            "2025-05-17",
            "2025-05-24"
        ],
        "q0.025": [
            34.0,
            27.0,
            25.0,
            25.0
        ],
        "q0.25": [
            52.0,
            42.0,
            41.0,
            40.0
        ],
        "q0.5": [
            68.0,
            61.0,
            56.0,
            57.0
        ],
        "q0.75": [
            83.0,
            79.0,
            70.0,
            68.0
        ],
        "q0.975": [
            117.0,
            98.0,
            96.0,
            84.0
        ]
    },
    "CFA_Pyrenew-Pyrenew_HE_Flu": {
        "target_end_date": [
            "2025-05-03",
            "2025-05-10"
        ],
        "q0.025": [
            46.0,
            23.0
        ],
        "q0.25": [
            59.0,
            35.0
        ],
        "q0.5": [
            67.0,
            45.0
        ],
        "q0.75": [
            74.0,
            55.0
        ],
        "q0.975": [
            91.0,
            82.0
        ]
    },
    "UNC_IDD-InfluPaint": {
        "target_end_date": [
            "2025-05-03",
            "2025-05-10",
            "2025-05-17",
            "2025-05-24"
        ],
        "q0.025": [
            36.004184070286634,
            24.142215684182265,
            12.996956296918146,
            9.054620213341552
        ],
        "q0.25": [
            43.28527902380661,
            29.288368904765367,
            18.628933503811144,
            11.579209274326606
        ],
        "q0.5": [
            45.718345998863086,
            31.180835744525076,
            20.09670879017495,
            12.495629324207052
        ],
        "q0.75": [
            48.43285108470946,
            33.300248182395926,
            21.735789186144036,
            13.71059959252311
        ],
        "q0.975": [
            52.898809076864744,
            38.106947246004445,
            24.875062031260345,
            16.337850822668567
        ]
    },
    "UVAFluX-OptimWISE": {
        "target_end_date": [
            "2025-05-03",
            "2025-05-10",
            "2025-05-17",
            "2025-05-24"
        ],
        "q0.025": [
            23.0,
            18.0,
            23.0,
            21.0
        ],
        "q0.25": [
            42.0,
            33.0,
            44.0,
            50.0
        ],
        "q0.5": [
            70.0,
            61.0,
            92.0,
            112.0
        ],
        "q0.75": [
            100.0,
            104.0,
            147.0,
            183.0
        ],
        "q0.975": [
            157.0,
            188.0,
            245.0,
            324.0
        ]
    },
    "UMass-flusion": {
        "target_end_date": [
            "2025-05-03",
            "2025-05-10",
            "2025-05-17",
            "2025-05-24"
        ],
        "q0.025": [
            15.2472413875276,
            11.8516875665975,
            9.90475645733022,
            7.44980108581956
        ],
        "q0.25": [
            37.0925930944572,
            19.7805292885577,
            12.1295793624225,
            8.78902720121929
        ],
        "q0.5": [
            54.5599553665778,
            38.707716924645,
            27.9261249405838,
            22.8076292339751
        ],
        "q0.75": [
            73.3816340846072,
            68.0074585104019,
            63.8684809635288,
            67.0364960080023
        ],
        "q0.975": [
            131.333898528046,
            163.207510880512,
            207.285172025508,
            255.259711459054
        ]
    },
    "PSI-PROF": {
        "target_end_date": [
            "2025-05-03",
            "2025-05-10",
            "2025-05-17",
            "2025-05-24"
        ],
        "q0.025": [
            5.0,
            0.0,
            0.0,
            0.0
        ],
        "q0.25": [
            28.0,
            17.0,
            11.0,
            8.0
        ],
        "q0.5": [
            66.0,
            42.0,
            26.0,
            18.0
        ],
        "q0.75": [
            89.86,
            89.0,
            87.89,
            87.07
        ],
        "q0.975": [
            159.88,
            194.36,
            279.36,
            299.48
        ]
    },
    "FluSight-trained_mean": {
        "target_end_date": [
            "2025-05-03",
            "2025-05-10",
            "2025-05-17",
            "2025-05-24"
        ],
        "q0.025": [
            12.568925042745937,
            3.932642885224774,
            1.5700279443048761,
            1.1852801865246922
        ],
        "q0.25": [
            30.826276432773774,
            18.300217378674525,
            11.510408838890669,
            8.492713731954838
        ],
        "q0.5": [
            54.87329131027742,
            40.684705005225496,
            33.28904480967468,
            23.976520919068506
        ],
        "q0.75": [
            103.55442863926855,
            94.54059722092639,
            94.6003983994953,
            87.1512965076299
        ],
        "q0.975": [
            271.6177398622981,
            331.13528671701755,
            414.2380271668577,
            508.70544897481693
        ]
    },
    "LUcompUncertLab-chimera": {
        "target_end_date": [
            "2025-04-26",
            "2025-05-03",
            "2025-05-10",
            "2025-05-17"
        ],
        "q0.025": [
            41.0,
            29.0,
            14.0,
            8.0
        ],
        "q0.25": [
            79.0,
            60.0,
            33.0,
            22.0
        ],
        "q0.5": [
            115.0,
            90.0,
            50.0,
            35.0
        ],
        "q0.75": [
            155.0,
            130.0,
            76.0,
            55.0
        ],
        "q0.975": [
            309.0,
            267.0,
            159.0,
            115.0
        ]
    },
    "UMass-AR2": {
        "target_end_date": [
            "2025-05-03",
            "2025-05-10",
            "2025-05-17",
            "2025-05-24"
        ],
        "q0.025": [
            5.215392497595819,
            0.0,
            0.0,
            0.0
        ],
        "q0.25": [
            46.71755668405331,
            35.88845817166288,
            30.71322419059368,
            28.234629521534718
        ],
        "q0.5": [
            78.73980248439447,
            81.2076172736077,
            84.5203717944147,
            89.16891878834173
        ],
        "q0.75": [
            116.991333599511,
            149.25390436048102,
            172.68107230687332,
            194.69945629660816
        ],
        "q0.975": [
            224.27498838442256,
            333.3952019468631,
            448.88078517186455,
            569.2072025079398
        ]
    },
    "UGA_flucast-Scenariocast": {
        "target_end_date": [
            "2025-05-03",
            "2025-05-10",
            "2025-05-17",
            "2025-05-24"
        ],
        "q0.025": [
            9.0,
            7.0,
            6.0,
            3.0
        ],
        "q0.25": [
            32.0,
            27.0,
            23.0,
            20.0
        ],
        "q0.5": [
            54.0,
            48.0,
            42.0,
            38.0
        ],
        "q0.75": [
            87.0,
            75.0,
            69.0,
            62.0
        ],
        "q0.975": [
            173.0,
            158.0,
            157.0,
            147.0
        ]
    },
    "UGA_flucast-Copycat": {
        "target_end_date": [
            "2025-05-03",
            "2025-05-10",
            "2025-05-17",
            "2025-05-24"
        ],
        "q0.025": [
            28.0,
            17.0,
            9.0,
            6.0
        ],
        "q0.25": [
            51.0,
            40.0,
            31.0,
            25.0
        ],
        "q0.5": [
            67.0,
            59.0,
            54.0,
            53.0
        ],
        "q0.75": [
            85.0,
            80.0,
            80.0,
            77.0
        ],
        "q0.975": [
            125.0,
            146.0,
            169.0,
            184.0
        ]
    },
    "CMU-climate_baseline": {
        "target_end_date": [
            "2025-04-26",
            "2025-05-03",
            "2025-05-10",
            "2025-05-17",
            "2025-05-24"
        ],
        "q0.025": [
            4.5,
            4.5,
            2.5,
            1.5,
            1.0
        ],
        "q0.25": [
            12.0,
            10.875,
            7.958333333333334,
            7.458333333333333,
            6.458333333333334
        ],
        "q0.5": [
            41.00000000000003,
            26.250000000000018,
            16.75,
            15.0,
            12.000000000000002
        ],
        "q0.75": [
            112.29166666666671,
            80.9583333333334,
            74.20833333333334,
            61.50000000000003,
            60.291666666666714
        ],
        "q0.975": [
            355.4458333333319,
            342.2208333333331,
            342.6458333333327,
            343.1208333333332,
            343.84583333333256
        ]
    },
    "UM-DeepOutbreak": {
        "target_end_date": [
            "2025-05-03",
            "2025-05-10",
            "2025-05-17",
            "2025-05-24"
        ],
        "q0.025": [
            0.0,
            0.0,
            0.0,
            0.0
        ],
        "q0.25": [
            42.9553108215332,
            0.0,
            0.0,
            0.0
        ],
        "q0.5": [
            73.60023880004883,
            81.8137321472168,
            143.23767471313477,
            225.75970840454104
        ],
        "q0.75": [
            73.60023880004883,
            414.95447326570087,
            1039.2916145324707,
            1131.7181434631348
        ],
        "q0.975": [
            239.983585357666,
            457.5285835266113,
            1039.2916145324707,
            1131.7181434631348
        ]
    },
    "SigSci-TSENS": {
        "target_end_date": [
            "2025-05-03",
            "2025-05-10",
            "2025-05-17",
            "2025-05-24"
        ],
        "q0.025": [
            0.0,
            0.0,
            0.0,
            0.0
        ],
        "q0.25": [
            6.0,
            0.0,
            0.0,
            0.0
        ],
        "q0.5": [
            52.0,
            39.0,
            30.0,
            19.0
        ],
        "q0.75": [
            99.0,
            129.0,
            162.0,
            191.0
        ],
        "q0.975": [
            187.0,
            299.0,
            413.0,
            519.0
        ]
    },
    "CFA_Pyrenew-Pyrenew_H_Flu": {
        "target_end_date": [
            "2025-05-03",
            "2025-05-10"
        ],
        "q0.025": [
            27.975,
            11.0
        ],
        "q0.25": [
            46.0,
            28.0
        ],
        "q0.5": [
            59.0,
            45.0
        ],
        "q0.75": [
            75.0,
            75.0
        ],
        "q0.975": [
            121.02499999999986,
            206.02499999999986
        ]
    },
    "UVAFluX-Ensemble": {
        "target_end_date": [
            "2025-04-26",
            "2025-05-03",
            "2025-05-10",
            "2025-05-17",
            "2025-05-24"
        ],
        "q0.025": [
            46.0,
            0.0,
            0.0,
            0.0,
            0.0
        ],
        "q0.25": [
            75.0,
            11.0,
            0.0,
            33.0,
            0.0
        ],
        "q0.5": [
            96.0,
            101.0,
            84.0,
            123.0,
            78.0
        ],
        "q0.75": [
            113.0,
            118.0,
            131.0,
            144.0,
            158.0
        ],
        "q0.975": [
            141.0,
            149.0,
            169.0,
            181.0,
            202.0
        ]
    },
    "FluSight-baseline": {
        "target_end_date": [
            "2025-04-26",
            "2025-05-03",
            "2025-05-10",
            "2025-05-17",
            "2025-05-24"
        ],
        "q0.025": [
            81.0,
            0.0,
            0.0,
            0.0,
            0.0
        ],
        "q0.25": [
            81.0,
            60.0,
            16.0,
            0.0,
            0.0
        ],
        "q0.5": [
            81.0,
            81.0,
            81.0,
            81.0,
            81.0
        ],
        "q0.75": [
            81.0,
            102.0,
            160.0,
            222.0,
            279.0
        ],
        "q0.975": [
            81.0,
            623.0,
            721.0,
            805.0,
            874.0
        ]
    },
    "FluSight-lop_norm": {
        "target_end_date": [
            "2025-05-03",
            "2025-05-10",
            "2025-05-17",
            "2025-05-24"
        ],
        "q0.025": [
            0.0,
            0.0,
            0.0,
            0.0
        ],
        "q0.25": [
            39.0,
            25.0,
            16.0,
            8.0
        ],
        "q0.5": [
            65.0,
            52.0,
            48.0,
            36.0
        ],
        "q0.75": [
            95.0,
            89.0,
            100.0,
            82.0
        ],
        "q0.975": [
            366.0,
            435.0,
            495.0,
            492.0
        ]
    },
    "MOBS-GLEAM_FLUH": {
        "target_end_date": [
            "2025-04-26",
            "2025-05-03",
            "2025-05-10",
            "2025-05-17",
            "2025-05-24"
        ],
        "q0.025": [
            57.3,
            19.962,
            11.34,
            6.707,
            5.252
        ],
        "q0.25": [
            62.55,
            31.649,
            19.676,
            13.493,
            10.502
        ],
        "q0.5": [
            70.316,
            40.612,
            25.513,
            18.339,
            13.703
        ],
        "q0.75": [
            81.049,
            48.658,
            31.576,
            24.341,
            18.369
        ],
        "q0.975": [
            100.698,
            67.405,
            46.351,
            34.993,
            28.206
        ]
    },
    "UMass-trends_ensemble": {
        "target_end_date": [
            "2025-05-03",
            "2025-05-10",
            "2025-05-17",
            "2025-05-24"
        ],
        "q0.025": [
            9.5,
            0.0,
            0.0,
            0.0
        ],
        "q0.25": [
            26.5,
            6.0,
            0.0,
            0.0
        ],
        "q0.5": [
            60.0,
            47.5,
            41.0,
            40.5
        ],
        "q0.75": [
            89.0,
            75.5,
            74.0,
            77.0
        ],
        "q0.975": [
            107.0,
            132.0,
            149.0,
            158.5
        ]
    },
    "UI_CompEpi-EpiGen": {
        "target_end_date": [
            "2025-05-03",
            "2025-05-10",
            "2025-05-17",
            "2025-05-24"
        ],
        "q0.025": [
            0.0,
            0.0,
            0.0,
            0.0
        ],
        "q0.25": [
            0.0,
            0.0,
            0.0,
            0.0
        ],
        "q0.5": [
            30.0,
            23.0,
            17.0,
            14.0
        ],
        "q0.75": [
            185.0,
            214.0,
            227.0,
            238.0
        ],
        "q0.975": [
            479.0,
            549.0,
            614.0,
            609.0
        ]
    },
    "FluSight-trained_med": {
        "target_end_date": [
            "2025-05-03",
            "2025-05-10",
            "2025-05-17",
            "2025-05-24"
        ],
        "q0.025": [
            4.0,
            0.0,
            0.0,
            0.0
        ],
        "q0.25": [
            28.0,
            16.0,
            11.0,
            8.0
        ],
        "q0.5": [
            63.0,
            42.0,
            32.0,
            34.94
        ],
        "q0.75": [
            89.86,
            94.0,
            94.0,
            87.07
        ],
        "q0.975": [
            189.41606682615023,
            266.58,
            301.64,
            299.48
        ]
    },
    "Gatech-ensemble_point": {
        "target_end_date": [
            "2025-05-03",
            "2025-05-10",
            "2025-05-17",
            "2025-05-24"
        ],
        "q0.025": [
            20.0,
            16.0,
            3.0,
            0.0
        ],
        "q0.25": [
            72.0,
            82.0,
            53.0,
            0.0
        ],
        "q0.5": [
            112.0,
            137.0,
            103.0,
            2.0
        ],
        "q0.75": [
            161.0,
            207.0,
            169.0,
            21.0
        ],
        "q0.975": [
            279.0,
            378.0,
            341.0,
            112.0
        ]
    },
    "UGA_flucast-INFLAenza": {
        "target_end_date": [
            "2025-05-03",
            "2025-05-10",
            "2025-05-17",
            "2025-05-24"
        ],
        "q0.025": [
            34.0,
            24.0,
            18.0,
            13.0
        ],
        "q0.25": [
            54.0,
            44.0,
            36.0,
            30.0
        ],
        "q0.5": [
            68.0,
            59.0,
            51.0,
            45.0
        ],
        "q0.75": [
            84.0,
            79.0,
            73.0,
            66.0
        ],
        "q0.975": [
            129.0,
            137.0,
            137.02499999999964,
            133.02499999999964
        ]
    },
    "LosAlamos_NAU-CModel_Flu": {
        "target_end_date": [
            "2025-05-03",
            "2025-05-10",
            "2025-05-17",
            "2025-05-24"
        ],
        "q0.025": [
            14.0,
            11.0,
            9.0,
            7.0
        ],
        "q0.25": [
            101.0,
            85.0,
            70.0,
            57.0
        ],
        "q0.5": [
            216.0,
            184.0,
            151.0,
            124.0
        ],
        "q0.75": [
            421.0,
            352.0,
            298.0,
            251.0
        ],
        "q0.975": [
            1221.0,
            1022.0,
            922.0249999999978,
            806.0
        ]
    },
    "NEU_ISI-FluBcast": {
        "target_end_date": [
            "2025-05-03",
            "2025-05-10",
            "2025-05-17",
            "2025-05-24"
        ],
        "q0.025": [
            26.0,
            24.0,
            23.0,
            22.0
        ],
        "q0.25": [
            43.0,
            39.0,
            37.0,
            36.0
        ],
        "q0.5": [
            58.0,
            54.0,
            53.0,
            52.0
        ],
        "q0.75": [
            72.0,
            68.0,
            66.0,
            65.0
        ],
        "q0.975": [
            90.0,
            82.0,
            78.0,
            77.0
        ]
    },
    "FluSight-ensemble": {
        "target_end_date": [
            "2025-05-03",
            "2025-05-10",
            "2025-05-17",
            "2025-05-24"
        ],
        "q0.025": [
            14.0,
            5.0,
            2.0,
            1.0
        ],
        "q0.25": [
            37.0,
            20.0,
            13.0,
            9.0
        ],
        "q0.5": [
            65.0,
            48.0,
            35.0,
            32.0
        ],
        "q0.75": [
            85.0,
            82.0,
            80.0,
            68.0
        ],
        "q0.975": [
            165.0,
            191.0,
            208.0,
            204.0
        ]
    },
    "PSI-PROF_beta": {
        "target_end_date": [
            "2025-05-03",
            "2025-05-10",
            "2025-05-17",
            "2025-05-24"
        ],
        "q0.025": [
            4.0,
            1.0,
            0.0,
            0.0
        ],
        "q0.25": [
            34.52,
            20.0,
            13.0,
            9.0
        ],
        "q0.5": [
            83.9,
            66.0,
            50.13,
            34.94
        ],
        "q0.75": [
            93.0,
            94.0,
            94.0,
            93.56
        ],
        "q0.975": [
            283.56,
            266.58,
            301.64,
            325.2
        ]
    },
    "CMU-TimeSeries": {
        "target_end_date": [
            "2025-04-26",
            "2025-05-03",
            "2025-05-10",
            "2025-05-17",
            "2025-05-24"
        ],
        "q0.025": [
            13.082380539536114,
            7.258297997756376,
            3.1941624496270147,
            2.2375268237677277,
            1.6950086049087545
        ],
        "q0.25": [
            57.09546876393548,
            31.866847553974317,
            23.35765483822669,
            18.058133235412463,
            14.918091648015103
        ],
        "q0.5": [
            85.33529947537505,
            44.83831136512826,
            35.67346891469432,
            30.057520274765015,
            26.84119758412597
        ],
        "q0.75": [
            116.12977953476019,
            77.77866482726394,
            56.17322636152394,
            54.84276894958265,
            59.521455421630876
        ],
        "q0.975": [
            218.05069770341976,
            189.41606682615023,
            196.0261335056619,
            198.23764749718043,
            205.02779376394054
        ]
    },
    "ISU_NiemiLab-GPE": {
        "target_end_date": [
            "2025-05-03",
            "2025-05-10",
            "2025-05-17",
            "2025-05-24"
        ],
        "q0.025": [
            8.99892302991559,
            5.99904207048367,
            2.00138363425555,
            2.00054354127485
        ],
        "q0.25": [
            27.9971952348752,
            19.9965017554829,
            11.9994314427253,
            9.99949240257912
        ],
        "q0.5": [
            45.0032396524439,
            37.0016656749461,
            32.0058188408903,
            31.9957051492579
        ],
        "q0.75": [
            74.0660127991202,
            67.0543504649143,
            68.060065629708,
            64.056190287178
        ],
        "q0.975": [
            169.30363849383,
            190.319957078937,
            220.311138958682,
            241.413568999796
        ]
    },
    "MIGHTE-Nsemble": {
        "target_end_date": [
            "2025-05-03",
            "2025-05-10",
            "2025-05-17",
            "2025-05-24"
        ],
        "q0.025": [
            0.0,
            0.0,
            0.0,
            2.0
        ],
        "q0.25": [
            0.0,
            0.0,
            0.0,
            18.0
        ],
        "q0.5": [
            57.0,
            39.0,
            31.0,
            40.0
        ],
        "q0.75": [
            294.0,
            272.0,
            233.0,
            78.0
        ],
        "q0.975": [
            751.0,
            723.0,
            622.0,
            228.0
        ]
    },
    "NIH-Flu_ARIMA": {
        "target_end_date": [
            "2025-05-03",
            "2025-05-10",
            "2025-05-17",
            "2025-05-24"
        ],
        "q0.025": [
            39.0,
            17.0,
            9.0,
            6.0
        ],
        "q0.25": [
            56.0,
            41.0,
            33.0,
            28.0
        ],
        "q0.5": [
            63.0,
            53.0,
            46.0,
            41.0
        ],
        "q0.75": [
            69.0,
            66.0,
            62.0,
            61.0
        ],
        "q0.975": [
            102.0,
            114.0,
            137.0,
            150.0
        ]
    },
    "JHUAPL-DMD": {
        "target_end_date": [
            "2025-04-26",
            "2025-05-03",
            "2025-05-10",
            "2025-05-17",
            "2025-05-24"
        ],
        "q0.025": [
            0.0,
            0.0,
            0.0,
            0.0,
            0.0
        ],
        "q0.25": [
            0.0,
            0.0,
            0.0,
            0.0,
            0.0
        ],
        "q0.5": [
            73.79318496,
            36.4097189,
            23.38884301,
            30.01883354,
            7.10581398
        ],
        "q0.75": [
            299.395163,
            239.9294461,
            194.9661331,
            200.9283244,
            166.5870508
        ],
        "q0.975": [
            761.5990151,
            883.5678606,
            945.186653,
            969.0443363,
            1275.918741
        ]
    },
    "CEPH-Rtrend_fluH": {
        "target_end_date": [
            "2025-05-03",
            "2025-05-10",
            "2025-05-17",
            "2025-05-24"
        ],
        "q0.025": [
            17.0,
            2.0,
            0.0,
            0.0
        ],
        "q0.25": [
            37.0,
            16.0,
            6.0,
            2.0
        ],
        "q0.5": [
            55.0,
            38.0,
            27.0,
            17.0
        ],
        "q0.75": [
            81.0,
            83.0,
            83.0,
            79.0
        ],
        "q0.975": [
            156.0,
            305.0,
            512.0,
            664.0
        ]
    }
}